pici/__init__.py
pici/causal_model.py
pici/graph/__init__.py
pici/graph/graph.py
pici/graph/node.py
pici/identifier.py
pici/intervention_inference_algorithm/__init__.py
pici/intervention_inference_algorithm/column_generation/__init__.py
pici/intervention_inference_algorithm/column_generation/scalable_problem_column_gen.py
pici/intervention_inference_algorithm/column_generation/scalable_problem_init.py
pici/intervention_inference_algorithm/linear_programming/__init__.py
pici/intervention_inference_algorithm/linear_programming/linear_constraints.py
pici/intervention_inference_algorithm/linear_programming/mechanisms_generator.py
pici/intervention_inference_algorithm/linear_programming/obj_function_generator.py
pici/intervention_inference_algorithm/linear_programming/opt_problem_builder.py
pici/intervention_inference_algorithm/linear_programming/optimizers.py
pici/utils/__init__.py
pici/utils/_enum.py
pici/utils/data_gen.py
pici/utils/graph_plotter.py
pici/utils/parser.py
pici/utils/probabilities_helper.py
pici/utils/scalable_graphs_helper.py
pici/utils/types.py
pici-0.0.2.dist-info/LICENSE
pici-0.0.2.dist-info/METADATA
pici-0.0.2.dist-info/WHEEL
pici-0.0.2.dist-info/RECORD
