Metadata-Version: 2.3
Name: pici
Version: 0.0.2
Summary: Package for Partially Identifiable Causal Inference
License: Apache-2.0
Keywords: causal inference
Author: Daniel Lawand
Author-email: daniel.lawand@gmail.com
Requires-Python: >=3.10,<3.13
Classifier: License :: OSI Approved :: Apache Software License
Classifier: Programming Language :: Python :: 3
Classifier: Programming Language :: Python :: 3.10
Classifier: Programming Language :: Python :: 3.11
Classifier: Programming Language :: Python :: 3.12
Requires-Dist: dowhy (>=0.13,<0.14)
Requires-Dist: gurobipy (>=12.0.1,<13.0.0)
Requires-Dist: matplotlib (>=3.10.1,<4.0.0)
Requires-Dist: networkx (>=3.4.2,<4.0.0)
Requires-Dist: pandas (>=2.2.3,<3.0.0)
Requires-Dist: pgmpy (>=1.0.0,<2.0.0)
Requires-Dist: scipy (>=1.7,<1.14)
